regis/__init__.py
regis/core.py
pilab_regis-0.0.13.dist-info/METADATA
pilab_regis-0.0.13.dist-info/WHEEL
pilab_regis-0.0.13.dist-info/top_level.txt
pilab_regis-0.0.13.dist-info/RECORD
