Metadata-Version: 2.4
Name: pilab-regis
Version: 0.0.13
Summary: Implementation of regis
Author-email: Nicolas Delinte <nicolas.delinte@uclouvain.be>
License-Expression: GPL-3.0-only
Keywords: registration
Classifier: Intended Audience :: Science/Research
Classifier: Natural Language :: English
Classifier: Programming Language :: Python
Requires-Dist: dipy
Requires-Dist: nibabel
Requires-Dist: numpy
